cjdata/__init__.py
cjdata/__main__.py
cjdata/baostock_pipeline.py
cjdata/builder.py
cjdata/cli.py
cjdata/db.py
cjdata/local_data.py
cjdata/utils.py
cjdata/xtquant_pipeline.py
cjdata/__pycache__/__main__.cpython-312.pyc
cjdata-0.0.2.dist-info/METADATA
cjdata-0.0.2.dist-info/WHEEL
cjdata-0.0.2.dist-info/entry_points.txt
cjdata-0.0.2.dist-info/top_level.txt
cjdata-0.0.2.dist-info/RECORD
