Metadata-Version: 2.4
Name: cjdata
Version: 0.0.2
Summary: Utilities for building and querying local stock data from xtquant and baostock sources.
Requires-Python: >=3.10
Requires-Dist: pandas>=2.0
Requires-Dist: numpy>=1.23
Provides-Extra: baostock
Requires-Dist: baostock>=0.8.8; extra == "baostock"
Provides-Extra: progress
Requires-Dist: tqdm>=4.60; extra == "progress"
Provides-Extra: talib
Requires-Dist: TA-Lib>=0.4; extra == "talib"
Provides-Extra: all
Requires-Dist: baostock>=0.8.8; extra == "all"
Requires-Dist: tqdm>=4.60; extra == "all"
Requires-Dist: TA-Lib>=0.4; extra == "all"
Provides-Extra: dev
Requires-Dist: pytest>=7.0; extra == "dev"
